lambada/GUI.py
lambada/MonitoredApp.py
lambada/__init__.py
lambada/__main__.py
lambada_launcher-0.3.0.dist-info/METADATA
lambada_launcher-0.3.0.dist-info/WHEEL
lambada_launcher-0.3.0.dist-info/entry_points.txt
lambada_launcher-0.3.0.dist-info/top_level.txt
lambada_launcher-0.3.0.dist-info/RECORD
