Metadata-Version: 2.1
Name: lambada-launcher
Version: 0.3.0
Summary: Basic job launcher
Author-email: Fabien André <fabien@andre.bzh>
License: WTFPL
Project-URL: repository, https://gitlab.com/fabienandre/lambada
Classifier: Development Status :: 3 - Alpha
Classifier: Programming Language :: Python
Requires-Dist: toml
